electrode_visualizer/Application.py
electrode_visualizer/Parser.py
electrode_visualizer/__init__.py
electrode_visualizer/__main__.py
electrode_visualizer-1.0.1.dist-info/LICENSE
electrode_visualizer-1.0.1.dist-info/METADATA
electrode_visualizer-1.0.1.dist-info/WHEEL
electrode_visualizer-1.0.1.dist-info/RECORD
