Metadata-Version: 2.1
Name: electrode-visualizer
Version: 1.0.1
Summary: An application for visualizing EEG's stored in csv's, build with dearpygui
Home-page: https://github.com/IgnaciodelaTorreArias/electrode-visualizer/blob/main/LICENSE
Author: Ignacio de la Torre Arias
Author-email: ignaciodlta@gmail.com
Requires-Python: >=3.10,<4.0
Classifier: Programming Language :: Python :: 3
Classifier: Programming Language :: Python :: 3.10
Classifier: Programming Language :: Python :: 3.11
Classifier: Programming Language :: Python :: 3.12
Requires-Dist: dearpygui (>=1.11.1,<2.0.0)
Requires-Dist: pandas (>=2.2.1,<3.0.0)
Project-URL: Repository, https://github.com/IgnaciodelaTorreArias/electrode-visualizer/blob/main/LICENSE
